cpmd_cube_tools/__init__.py
cpmd_cube_tools/_citation.py
cpmd_cube_tools/_version.py
cpmd_cube_tools/api.py
cpmd_cube_tools/core.py
cpmd_cube_tools/main.py
cpmd_cube_tools/test/DENSITY.cube
cpmd_cube_tools/test/GEOMETRY
cpmd_cube_tools/test/mm2qm_overlap.inp
cpmd_cube_tools-0.993.data/scripts/cubetool.py
cpmd_cube_tools-0.993.data/scripts/test.py
cpmd_cube_tools-0.993.dist-info/LICENSE
cpmd_cube_tools-0.993.dist-info/METADATA
cpmd_cube_tools-0.993.dist-info/WHEEL
cpmd_cube_tools-0.993.dist-info/top_level.txt
cpmd_cube_tools-0.993.dist-info/RECORD
