Metadata-Version: 2.1
Name: cpmd-cube-tools
Version: 0.993
Summary: A python library and tool to read in and manipulate Gaussian and CPMD cube files.
Home-page: https://gitlab.com/WadeHPCLEAP/cube_tools.git
Author: Wenping Lyu
Author-email: lyuwade@gmail.com
License: UNKNOWN
Platform: UNKNOWN
Classifier: Programming Language :: Python :: 3
Classifier: Operating System :: OS Independent
Requires-Python: >=3.6
Requires-Dist: pandas (>=0.24.2)
Requires-Dist: numpy (>=1.17.2)
Requires-Dist: scipy (>=1.4.1)
Requires-Dist: scikit-image (>=0.15.0)
